LICENSE.txt
MANIFEST.in
README.md
setup.cfg
setup.py
pdf_cut/PdfCutF.pyd
pdf_cut/PdfCutResulUI.pyd
pdf_cut/PdfCutUI.pyd
pdf_cut/Pdf_Cut.pyd
pdf_cut/__init__.py
pdf_cut/pdf_result_tables.pyd
pdf_cut.egg-info/PKG-INFO
pdf_cut.egg-info/SOURCES.txt
pdf_cut.egg-info/dependency_links.txt
pdf_cut.egg-info/top_level.txt