Metadata-Version: 2.1
Name: pdf-cut
Version: 0.1.9
Summary: 剪切pdf中黑色边框
Home-page: https://alidocs.dingtalk.com/i/p/4oJRz0VRJyvmLZMydy0mV7WvjQn7MG89
Author: wangweidong
Author-email: 17891967090@163.com
Classifier: Programming Language :: Python
Requires-Python: >=3.8
License-File: LICENSE.txt
